snakemake/__init__.py
snakemake/__main__.py
snakemake/_version.py
snakemake/benchmark.py
snakemake/checkpoints.py
snakemake/common.py
snakemake/conda.py
snakemake/cwl.py
snakemake/dag.py
snakemake/decorators.py
snakemake/exceptions.py
snakemake/executors.py
snakemake/gui.html
snakemake/gui.py
snakemake/io.py
snakemake/jobs.py
snakemake/jobscript.sh
snakemake/logging.py
snakemake/output_index.py
snakemake/parser.py
snakemake/persistence.py
snakemake/report.css
snakemake/rules.py
snakemake/scheduler.py
snakemake/script.py
snakemake/shell.py
snakemake/singularity.py
snakemake/stats.py
snakemake/utils.py
snakemake/workflow.py
snakemake/wrapper.py
snakemake/remote/EGA.py
snakemake/remote/FTP.py
snakemake/remote/GS.py
snakemake/remote/HTTP.py
snakemake/remote/NCBI.py
snakemake/remote/S3.py
snakemake/remote/S3Mocked.py
snakemake/remote/SFTP.py
snakemake/remote/XRootD.py
snakemake/remote/__init__.py
snakemake/remote/dropbox.py
snakemake/remote/gfal.py
snakemake/remote/gridftp.py
snakemake/remote/iRODS.py
snakemake/remote/webdav.py
snakemake/report/__init__.py
snakemake/report/report.html
snakemake_py37-5.4.6.dist-info/AUTHORS.rst
snakemake_py37-5.4.6.dist-info/LICENSE.md
snakemake_py37-5.4.6.dist-info/METADATA
snakemake_py37-5.4.6.dist-info/WHEEL
snakemake_py37-5.4.6.dist-info/entry_points.txt
snakemake_py37-5.4.6.dist-info/top_level.txt
snakemake_py37-5.4.6.dist-info/RECORD
